aps_cli/_init_.py
aps_cli/app.py
aps_cli/schema_min.py
aps_cli/signing.py
aps_cli/templates/aps-manifest.yaml
aps_cli/templates/echo_agent/AGENT_CARD.md
aps_cli/templates/echo_agent/README.md
aps_cli/templates/echo_agent/aps/agent.yaml
aps_cli/templates/echo_agent/src/echo/main.py
apstool-0.1.11.dist-info/METADATA
apstool-0.1.11.dist-info/WHEEL
apstool-0.1.11.dist-info/entry_points.txt
apstool-0.1.11.dist-info/top_level.txt
apstool-0.1.11.dist-info/RECORD
