Metadata-Version: 2.4
Name: apstool
Version: 0.1.11
Summary: Command-line tool for the Agent Packaging Standard (APS)
Author-email: Veda Hegde <vedahegde60@gmail.com>
License-Expression: Apache-2.0
Project-URL: Homepage, https://agentpackaging.org
Project-URL: Documentation, https://agentpackaging.org
Project-URL: Repository, https://github.com/vedahegde60/agent-packaging-standard
Project-URL: Issues, https://github.com/vedahegde60/agent-packaging-standard/issues
Keywords: ai,agents,packaging,aps,agent-packaging-standard,cli
Classifier: Development Status :: 3 - Alpha
Classifier: Intended Audience :: Developers
Classifier: Programming Language :: Python :: 3
Classifier: Programming Language :: Python :: 3.10
Classifier: Programming Language :: Python :: 3.11
Classifier: Programming Language :: Python :: 3.12
Classifier: Programming Language :: Python :: 3.13
Classifier: Programming Language :: Python :: 3.14
Classifier: Topic :: Software Development :: Libraries
Classifier: Topic :: Software Development :: Build Tools
Requires-Python: >=3.10
Requires-Dist: pyyaml>=6.0.1
Requires-Dist: requests>=2.31
Provides-Extra: dev
Requires-Dist: pytest>=7.0; extra == "dev"
Requires-Dist: scikit-learn>=1.3; extra == "dev"
Requires-Dist: cryptography>=41.0; extra == "dev"
